baldrapp/__init__.py
baldrapp/apps/__init__.py
baldrapp/apps/baldr_alignment_app/Baldr_Fresnel_App.py
baldrapp/apps/baldr_alignment_app/__init__.py
baldrapp/apps/baldr_closed_loop_app/__init__.py
baldrapp/apps/baldr_closed_loop_app/closed_loop_pyqtgraph.py
baldrapp/common/DM_basis.py
baldrapp/common/DM_registration.py
baldrapp/common/__init__.py
baldrapp/common/baldr_core.py
baldrapp/common/baldr_experiments.py
baldrapp/common/phasescreens.py
baldrapp/common/pupils.py
baldrapp/common/utilities.py
baldrapp/configurations/BALDR_UT_J3.ini
baldrapp/configurations/__init__.py
baldrapp/configurations/strehl_model_config-BALDR_UT_J3_2024-10-19T09.28.27.pkl
baldrapp/data/Exposed_Ma-N_1405_optical_constants.txt
baldrapp/data/__init__.py
baldrapp/playground/IM_onsky_sim.py
baldrapp/playground/__init__.py
baldrapp/playground/calibrating_optical_gain_model_v1 copy.py
baldrapp/playground/closedloop.py
baldrapp/playground/closedloop_internal_ab.py
baldrapp/playground/effect_pupil_definition.py
baldrapp/playground/fit_cauchy_eq_Ma-N_1405_photoresist.py
baldrapp/playground/full_sim_fresnel.py
baldrapp/playground/just_play.py
baldrapp/playground/kalman_play.py
baldrapp/playground/lucky_imaging_example.py
baldrapp/playground/open_to_closedloop.py
baldrapp/playground/phasemask_fine_acquisition_simulation.py
baldrapp/playground/pyzelda_play.py
baldrapp/playground/reviewing_for_writeup.py
baldrapp/playground/scintillation_theory_sim_check.py
baldrapp/playground/test_tutorial_baldr.py
baldrapp/playground/theoretical_pupils.py
baldrapp/playground/verify_experiment_module.py
baldrapp/playground/verify_updates.py
baldrapp/playground/visual_exploration_optical_gain.py
baldrapp-0.1.8.data/scripts/Baldr_Fresnel_App.py
baldrapp-0.1.8.data/scripts/closed_loop_pyqtgraph.py
baldrapp-0.1.8.dist-info/licenses/LICENSE
baldrapp-0.1.8.dist-info/METADATA
baldrapp-0.1.8.dist-info/WHEEL
baldrapp-0.1.8.dist-info/top_level.txt
baldrapp-0.1.8.dist-info/RECORD
